cased_kit-3.5.1.dist-info/licenses/LICENSE
kit/__init__.py
kit/ast_search.py
kit/cli.py
kit/code_searcher.py
kit/context_extractor.py
kit/deep_research.py
kit/doc_providers.py
kit/docstring_indexer.py
kit/incremental_analyzer.py
kit/llm_client_factory.py
kit/llm_context.py
kit/multi_repo.py
kit/ollama_client.py
kit/package_search.py
kit/repo_mapper.py
kit/repository.py
kit/summaries.py
kit/tool_schemas.py
kit/tree_sitter_symbol_extractor.py
kit/utils.py
kit/vector_searcher.py
kit/api/__init__.py
kit/api/app.py
kit/api/registry.py
kit/dependency_analyzer/__init__.py
kit/dependency_analyzer/dependency_analyzer.py
kit/dependency_analyzer/go_dependency_analyzer.py
kit/dependency_analyzer/javascript_dependency_analyzer.py
kit/dependency_analyzer/python_dependency_analyzer.py
kit/dependency_analyzer/rust_dependency_analyzer.py
kit/dependency_analyzer/terraform_dependency_analyzer.py
kit/mcp/__init__.py
kit/mcp/__main__.py
kit/mcp/dev.py
kit/mcp/dev_server.py
kit/pr_review/__init__.py
kit/pr_review/__main__.py
kit/pr_review/agentic_reviewer.py
kit/pr_review/base_reviewer.py
kit/pr_review/cache.py
kit/pr_review/commit_generator.py
kit/pr_review/config.py
kit/pr_review/cost_tracker.py
kit/pr_review/debug.py
kit/pr_review/diff_parser.py
kit/pr_review/file_prioritizer.py
kit/pr_review/line_ref_fixer.py
kit/pr_review/local_reviewer.py
kit/pr_review/matrix_tester.py
kit/pr_review/priority_filter.py
kit/pr_review/priority_utils.py
kit/pr_review/profile_manager.py
kit/pr_review/reviewer.py
kit/pr_review/summarizer.py
kit/pr_review/test_accuracy.py
kit/pr_review/validator.py
kit/queries/c/tags.scm
kit/queries/cpp/tags.scm
kit/queries/csharp/tags.scm
kit/queries/dart/tags.scm
kit/queries/go/tags.scm
kit/queries/haskell/tags.scm
kit/queries/hcl/tags.scm
kit/queries/java/tags.scm
kit/queries/javascript/tags.scm
kit/queries/kotlin/tags.scm
kit/queries/python/tags.scm
kit/queries/ruby/tags.scm
kit/queries/rust/tags.scm
kit/queries/typescript/tags.scm
kit/queries/zig/tags.scm
cased_kit-3.5.1.dist-info/METADATA
cased_kit-3.5.1.dist-info/WHEEL
cased_kit-3.5.1.dist-info/entry_points.txt
cased_kit-3.5.1.dist-info/top_level.txt
cased_kit-3.5.1.dist-info/RECORD
