Metadata-Version: 2.4
Name: cased-kit
Version: 3.5.1
Summary: A modular toolkit for LLM-powered codebase understanding.
Author-email: Cased <ted@cased.com>
License: MIT
Project-URL: Homepage, https://github.com/cased/kit
Requires-Python: >=3.10
License-File: LICENSE
Requires-Dist: tree-sitter>=0.25.1
Requires-Dist: tree-sitter-language-pack>=0.7.2
Requires-Dist: pathspec>=0.11.1
Requires-Dist: ignore-python>=0.3.0
Requires-Dist: numpy>=1.25
Requires-Dist: fastapi>=0.110.0
Requires-Dist: uvicorn[standard]>=0.20
Requires-Dist: typer<0.16,>=0.9
Requires-Dist: click<8.2,>=8.0
Requires-Dist: openai>=1.0.0
Requires-Dist: tiktoken>=0.4.0
Requires-Dist: anthropic>=0.20.0
Requires-Dist: google-genai>=1.14.0
Requires-Dist: python-hcl2>=7.2.0
Requires-Dist: mcp<2.0.0,>=1.23.0
Requires-Dist: redis>=5.0.0
Requires-Dist: requests>=2.25.0
Requires-Dist: pyyaml>=6.0
Requires-Dist: tomli>=2.0.0; python_version < "3.11"
Provides-Extra: dev
Requires-Dist: build; extra == "dev"
Requires-Dist: twine; extra == "dev"
Provides-Extra: test-api
Requires-Dist: fastapi; extra == "test-api"
Requires-Dist: pytest; extra == "test-api"
Provides-Extra: ml
Requires-Dist: sentence-transformers>=2.2.0; extra == "ml"
Requires-Dist: chromadb>=1.0.0; extra == "ml"
Provides-Extra: all
Requires-Dist: sentence-transformers>=2.2.0; extra == "all"
Requires-Dist: chromadb>=1.0.0; extra == "all"
Dynamic: license-file
